LerEscreverInfo/__init__.py
LerEscreverInfo/armazenamento.py
LerEscreverInfo/consulta.py
LerEscreverInfo/interacao.py
LerEscreverInfo-0.0.1.dist-info/LICENSE
LerEscreverInfo-0.0.1.dist-info/METADATA
LerEscreverInfo-0.0.1.dist-info/WHEEL
LerEscreverInfo-0.0.1.dist-info/top_level.txt
LerEscreverInfo-0.0.1.dist-info/RECORD
