Metadata-Version: 2.1
Name: LerEscreverInfo
Version: 0.0.1
Summary: Pacote python para cadastrar e ler informações como o nome, o CPF e o endereco
Home-page: UNKNOWN
Author: Pedro Benitah Vieira Sanchez de Melo
Author-email: pedrobenitah@gmail.com
License: MIT License
Keywords: Pacote
Platform: UNKNOWN
License-File: LICENSE
